purecpp_docling/__init__.py
purecpp_docling/loader.py
purecpp_docling-1.0.0.dist-info/licenses/LICENSE
purecpp_docling-1.0.0.dist-info/METADATA
purecpp_docling-1.0.0.dist-info/WHEEL
purecpp_docling-1.0.0.dist-info/top_level.txt
purecpp_docling-1.0.0.dist-info/RECORD
