Metadata-Version: 2.4
Name: purecpp-docling
Version: 1.0.0
Summary: Docling PureCPP integration
Author-email: Gabriel Ayres <gabriel.ayres@pureai.com.br>
Maintainer-email: Gabriel Ayres <gabriel.ayres@pureai.com.br>
License-Expression: MIT
Requires-Python: >=3.9
License-File: LICENSE
Requires-Dist: docling>=2.41.0
Requires-Dist: purecpp>=0.0.12
Requires-Dist: purecpp-extract>=0.0.12
Requires-Dist: purecpp-libs>=0.0.12
Dynamic: license-file
